Metadata-Version: 2.1
Name: django4-tabbed-admin
Version: 1.0.5
Summary: Easily add tabs to django admin forms.
Home-page: http://www.revsquare.com
Author: Guillaume Pousseo, Tharushan
Author-email: guillaumepousseo@revsquare.com, contact@tharushan.fr
License: BSD License
Platform: OS Independent
Classifier: Development Status :: 5 - Production/Stable
Classifier: Environment :: Web Environment
Classifier: Framework :: Django
Classifier: Intended Audience :: Developers
Classifier: License :: OSI Approved :: BSD License
Classifier: Operating System :: OS Independent
Classifier: Programming Language :: Python
Classifier: Programming Language :: Python :: 3.8
License-File: LICENSE.txt
License-File: AUTHORS.txt
